freesimplesql/__init__.py
freesimplesql/__main__.py
freesimplesql/main.py
freesimplesql-0.3.0.dist-info/METADATA
freesimplesql-0.3.0.dist-info/WHEEL
freesimplesql-0.3.0.dist-info/entry_points.txt
freesimplesql-0.3.0.dist-info/RECORD
