Metadata-Version: 2.4
Name: freesimplesql
Version: 0.3.0
Summary: A SQLite database browser, editor and AI query builder using FreeSimpleGUI
Project-URL: Homepage, https://github.com/fxyzbtc/freesimplesql
Project-URL: Repository, https://github.com/fxyzbtc/freesimplesql
Project-URL: Bug Tracker, https://github.com/fxyzbtc/freesimplesql/issues
Project-URL: Documentation, https://github.com/fxyzbtc/freesimplesql#readme
License: MIT
Keywords: ai,browser,database,editor,gui,sql,sqlite
Classifier: Development Status :: 4 - Beta
Classifier: Intended Audience :: Developers
Classifier: License :: OSI Approved :: MIT License
Classifier: Programming Language :: Python :: 3
Classifier: Programming Language :: Python :: 3.7
Classifier: Programming Language :: Python :: 3.8
Classifier: Programming Language :: Python :: 3.9
Classifier: Programming Language :: Python :: 3.10
Classifier: Programming Language :: Python :: 3.11
Classifier: Programming Language :: Python :: 3.12
Classifier: Topic :: Database
Classifier: Topic :: Software Development :: User Interfaces
Requires-Python: >=3.7
Requires-Dist: faker>=18.13.0
Requires-Dist: freesimplegui>=5.2.0.post1
Requires-Dist: loguru>=0.7.3
Requires-Dist: python-dateutil>=2.8.2
Requires-Dist: requests>=2.31.0
Requires-Dist: sqlmodel>=0.0.24
